./.gitignore
./PKG-INFO
./README.md
./pyproject.toml
./mp_scrape_export_sqlite/__init__.py
mp_scrape_export_sqlite-0.1.1.dist-info/METADATA
mp_scrape_export_sqlite-0.1.1.dist-info/WHEEL
mp_scrape_export_sqlite-0.1.1.dist-info/RECORD
