Metadata-Version: 2.4
Name: mp_scrape_export_sqlite
Version: 0.1.1
Summary: Export data as SQLite
Project-URL: Homepage, https://git.fsfe.org/mp-scrape/mp-scrape
Project-URL: Issues, https://git.fsfe.org/mp-scrape/mp-scrape/issues
Author-email: "Free Software Foundation Europe e.V." <mp-scrape@fsfe.org>
Maintainer-email: Sofía Aritz <sofiaritz@fsfe.org>
License-Expression: AGPL-3.0-only
Classifier: Development Status :: 4 - Beta
Classifier: Intended Audience :: Developers
Classifier: License :: OSI Approved :: GNU Affero General Public License v3
Classifier: Programming Language :: Python :: 3.11
Classifier: Typing :: Typed
Requires-Python: >=3.11
Requires-Dist: mp-scrape-core>=0.1.0
Requires-Dist: pandas>=2
